[
  {
    "source": "./model/icon.png",
    "outDirectory": "res/icons",
    "sizes": [
      {
        "fileName": "iphone_2x.png",
        "width": 120,
        "height": 120
      },
      {
        "fileName": "iphone_3x.png",
        "width": 180,
        "height": 180
      },
      {
        "fileName": "ipad.png",
        "width": 76,
        "height": 76
      },
      {
        "fileName": "ipad_2x.png",
        "width": 152,
        "height": 152
      },
      {
        "fileName": "ipad_pro.png",
        "width": 167,
        "height": 167
      },
      {
        "fileName": "ios_settings.png",
        "width": 29,
        "height": 29
      },
      {
        "fileName": "ios_settings_2x.png",
        "width": 58,
        "height": 58
      },
      {
        "fileName": "ios_settings_3x.png",
        "width": 87,
        "height": 87
      },
      {
        "fileName": "ios_spotlight.png",
        "width": 40,
        "height": 40
      },
      {
        "fileName": "ios_spotlight_2x.png",
        "width": 80,
        "height": 80
      },
      {
        "fileName": "android_mdpi.png",
        "width": 48,
        "height": 48
      },
      {
        "fileName": "android_hdpi.png",
        "width": 72,
        "height": 72
      },
      {
        "fileName": "android_xhdpi.png",
        "width": 96,
        "height": 96
      },
      {
        "fileName": "android_xxhdpi.png",
        "width": 144,
        "height": 144
      },
      {
        "fileName": "android_xxxhdpi.png",
        "width": 192,
        "height": 192
      }
    ]
  },
  {
    "source": "./model/splash.png",
    "outDirectory": "res/splash",
    "isCrop": true,
    "sizes": [
      {
        "fileName": "iphone_2x.png",
        "width": 640,
        "height": 960
      },
      {
        "fileName": "iphone5.png",
        "width": 640,
        "height": 1136
      },
      {
        "fileName": "iphone6.png",
        "width": 750,
        "height": 1334
      },
      {
        "fileName": "iphone6p_portrait.png",
        "width": 1242,
        "height": 2208
      },
      {
        "fileName": "iphone6p_landscape.png",
        "width": 2208,
        "height": 1242
      },
      {
        "fileName": "ipad_portrait.png",
        "width": 768,
        "height": 1024
      },
      {
        "fileName": "ipad_portrait_2x.png",
        "width": 1536,
        "height": 2048
      },
      {
        "fileName": "ipad_landscape.png",
        "width": 1024,
        "height": 768
      },
      {
        "fileName": "ipad_landscape_2x.png",
        "width": 2048,
        "height": 1536
      },
      {
        "fileName": "android_mdpi_portrait.png",
        "width": 320,
        "height": 470
      },
      {
        "fileName": "android_mdpi_landscape.png",
        "width": 470,
        "height": 320
      },
      {
        "fileName": "android_hdpi_portrait.png",
        "width": 480,
        "height": 640
      },
      {
        "fileName": "android_hdpi_landscape.png",
        "width": 640,
        "height": 480
      },
      {
        "fileName": "android_xhdpi_portrait.png",
        "width": 720,
        "height": 960
      },
      {
        "fileName": "android_xhdpi_landscape.png",
        "width": 960,
        "height": 720
      },
      {
        "fileName": "android_xxhdpi_portrait.png",
        "width": 1080,
        "height": 1440
      },
      {
        "fileName": "android_xxhdpi_landscape.png",
        "width": 1440,
        "height": 1080
      }
    ]
  }
]

